negmas_genius_agents/__init__.py
negmas_genius_agents/py.typed
negmas_genius_agents/registry_init.py
negmas_genius_agents/negotiators/__init__.py
negmas_genius_agents/negotiators/time_dependent.py
negmas_genius_agents/negotiators/anac/__init__.py
negmas_genius_agents/negotiators/anac/y2010/__init__.py
negmas_genius_agents/negotiators/anac/y2010/agent_fsega.py
negmas_genius_agents/negotiators/anac/y2010/agent_k.py
negmas_genius_agents/negotiators/anac/y2010/agent_smith.py
negmas_genius_agents/negotiators/anac/y2010/iam_crazy_haggler.py
negmas_genius_agents/negotiators/anac/y2010/iam_haggler.py
negmas_genius_agents/negotiators/anac/y2010/nozomi.py
negmas_genius_agents/negotiators/anac/y2010/yushu.py
negmas_genius_agents/negotiators/anac/y2011/__init__.py
negmas_genius_agents/negotiators/anac/y2011/agent_k2.py
negmas_genius_agents/negotiators/anac/y2011/bram_agent.py
negmas_genius_agents/negotiators/anac/y2011/gahboninho.py
negmas_genius_agents/negotiators/anac/y2011/hard_headed.py
negmas_genius_agents/negotiators/anac/y2011/iam_haggler.py
negmas_genius_agents/negotiators/anac/y2011/the_negotiator.py
negmas_genius_agents/negotiators/anac/y2012/__init__.py
negmas_genius_agents/negotiators/anac/y2012/agent_lg.py
negmas_genius_agents/negotiators/anac/y2012/agent_mr.py
negmas_genius_agents/negotiators/anac/y2012/cuhk_agent.py
negmas_genius_agents/negotiators/anac/y2012/iam_haggler2012.py
negmas_genius_agents/negotiators/anac/y2012/meta_agent.py
negmas_genius_agents/negotiators/anac/y2012/omac_agent.py
negmas_genius_agents/negotiators/anac/y2012/the_negotiator_reloaded.py
negmas_genius_agents/negotiators/anac/y2013/__init__.py
negmas_genius_agents/negotiators/anac/y2013/agent_kf.py
negmas_genius_agents/negotiators/anac/y2013/g_agent.py
negmas_genius_agents/negotiators/anac/y2013/inox_agent.py
negmas_genius_agents/negotiators/anac/y2013/meta_agent.py
negmas_genius_agents/negotiators/anac/y2013/slava_agent.py
negmas_genius_agents/negotiators/anac/y2013/the_fawkes.py
negmas_genius_agents-0.2.1.dist-info/METADATA
negmas_genius_agents-0.2.1.dist-info/WHEEL
negmas_genius_agents-0.2.1.dist-info/licenses/LICENSE
negmas_genius_agents-0.2.1.dist-info/RECORD
