Metadata-Version: 2.4
Name: negmas-genius-agents
Version: 0.2.1
Summary: Python reimplementations of Genius negotiating agents for NegMAS
Author-email: Yasser Mohammad <yasserfarouk@gmail.com>
License-Expression: AGPL-3.0-or-later
License-File: LICENSE
Requires-Python: >=3.10
Requires-Dist: negmas>=0.14.0
Requires-Dist: numpy>=1.24.0
